dialog_lib/agents/__init__.py
dialog_lib/agents/abstract.py
dialog_lib/agents/anthropic.py
dialog_lib/agents/openai.py
dialog_lib/db/__init__.py
dialog_lib/db/memory.py
dialog_lib/db/models.py
dialog_lib/db/session.py
dialog_lib/db/utils.py
dialog_lib/embeddings/__init__.py
dialog_lib/embeddings/generate.py
dialog_lib/embeddings/retrievers.py
dialog_lib/loaders/__init__.py
dialog_lib/loaders/csv.py
dialog_lib/loaders/gsheets.py
dialog_lib/loaders/web.py
dialog_lib/manage.py
dialog_lib/memory.py
dialog_lib/tests/__init__.py
dialog_lib/tests/agents/__init__.py
dialog_lib/tests/agents/test_abstract_agents.py
dialog_lib/tests/agents/test_third_party_agents.py
dialog_lib/tests/conftest.py
dialog_lib/tests/db/__init__.py
dialog_lib/tests/db/test_embedding_generation.py
dialog_lib/tests/db/test_memory.py
dialog_lib/tests/fixtures/__init__.py
dialog_lib/tests/fixtures/embedding_model.py
dialog_lib/tests/loaders/__init__.py
dialog_lib/tests/loaders/test_web_loader.py
dialog_lib-0.0.3.0.dist-info/METADATA
dialog_lib-0.0.3.0.dist-info/WHEEL
dialog_lib-0.0.3.0.dist-info/entry_points.txt
dialog_lib-0.0.3.0.dist-info/RECORD
