Metadata-Version: 2.1
Name: dialog-lib
Version: 0.0.3.0
Summary: 
License: MIT
Author: Talkd.AI
Author-email: foss@talkd.ai
Requires-Python: >=3.11,<4.0
Classifier: License :: OSI Approved :: MIT License
Classifier: Programming Language :: Python :: 3
Classifier: Programming Language :: Python :: 3.11
Classifier: Programming Language :: Python :: 3.12
Classifier: Programming Language :: Python :: 3.13
Requires-Dist: SQLAlchemy (==2.0.29)
Requires-Dist: aioresponses (==0.7.6)
Requires-Dist: bs4 (==0.0.2)
Requires-Dist: click (==8.1.7)
Requires-Dist: gspread (==6.1.2)
Requires-Dist: langchain (==0.2.10)
Requires-Dist: langchain-anthropic (==0.1.20)
Requires-Dist: langchain-community (==0.2.9)
Requires-Dist: langchain-openai (==0.1.8)
Requires-Dist: langchain-postgres (==0.0.12)
Requires-Dist: pgvector (==0.2.5)
Requires-Dist: psycopg (>=3.2.2,<4.0.0)
Requires-Dist: psycopg-pool (>=3.2.3,<4.0.0)
Requires-Dist: psycopg2 (==2.9.9)
Requires-Dist: pytest-asyncio (==0.23.6)
Requires-Dist: responses (==0.25.0)
